helmpy/__init__.py
helmpy/core/__init__.py
helmpy/core/helm_ds_m1_pv1.py
helmpy/core/helm_ds_m1_pv2.py
helmpy/core/helm_ds_m2_pv1.py
helmpy/core/helm_ds_m2_pv2.py
helmpy/core/helm_epsilon_algorithm.py
helmpy/core/helm_pade.py
helmpy/core/helm_pv1.py
helmpy/core/helm_pv2.py
helmpy/core/nr.py
helmpy/core/nr_ds.py
helmpy/core/write_results_to_csv.py
helmpy-0.1.0rc20190802075106.dist-info/LICENSE.txt
helmpy-0.1.0rc20190802075106.dist-info/METADATA
helmpy-0.1.0rc20190802075106.dist-info/WHEEL
helmpy-0.1.0rc20190802075106.dist-info/top_level.txt
helmpy-0.1.0rc20190802075106.dist-info/RECORD
