Metadata-Version: 2.1
Name: helmpy
Version: 0.1.0rc20190802075106
Summary: HELMpy is an open source package of power flow solvers, including the Holomorphic Embedding Load Flow Method (HELM).
Home-page: https://github.com/HELMpy/HELMpy
License: UNKNOWN
Platform: UNKNOWN
